synapse_ast.py
synapse_interpreter.py
synapse_jit.py
synapse_parser.py
synapse_repl.py
synapse_scientific.py
quantum_net_lang/__init__.py
qubit_flow_lang/__init__.py
synapse_lang/__init__.py
synapse_lang/__version__.py
synapse_lang/ast_consolidated.py
synapse_lang/distributed_computing.py
synapse_lang/errors.py
synapse_lang/jit_compiler.py
synapse_lang/license_manager.py
synapse_lang/ml_integration.py
synapse_lang/parallel.py
synapse_lang/parser_enhanced.py
synapse_lang/security.py
synapse_lang/stdlib.py
synapse_lang/symbolic.py
synapse_lang/synapse_ast.py
synapse_lang/synapse_ast_enhanced.py
synapse_lang/synapse_interpreter.py
synapse_lang/synapse_lexer.py
synapse_lang/synapse_parser.py
synapse_lang/synapse_parser_enhanced.py
synapse_lang/synapse_parser_minimal.py
synapse_lang/tensor_ops.py
synapse_lang/type_system.py
synapse_lang/uncertainty.py
synapse_lang/pharmkit/__init__.py
synapse_lang/pharmkit/docking.py
synapse_lang/pharmkit/molecular.py
synapse_lang/pharmkit/qsar.py
synapse_lang/quantum/__init__.py
synapse_lang/quantum/algorithms.py
synapse_lang/quantum/core.py
synapse_lang/quantum/semantics.py
synapse_lang-2.2.0.dist-info/licenses/AUTHORS.md
synapse_lang-2.2.0.dist-info/licenses/LICENSE
synapse_lang-2.2.0.dist-info/licenses/LICENSE-COMMUNITY
synapse_lang-2.2.0.dist-info/licenses/LICENSE-DUAL.md
synapse_lang-2.2.0.dist-info/licenses/LICENSE-PROPRIETARY
synapse_lang-2.2.0.dist-info/licenses/license_server.py
synapse_lang-2.2.0.dist-info/METADATA
synapse_lang-2.2.0.dist-info/WHEEL
synapse_lang-2.2.0.dist-info/entry_points.txt
synapse_lang-2.2.0.dist-info/top_level.txt
synapse_lang-2.2.0.dist-info/RECORD
